{
    "haskellNix": {
        "branch": "master",
        "description": "Alternative Haskell Infrastructure for Nixpkgs",
        "homepage": "https://input-output-hk.github.io/haskell.nix",
        "owner": "input-output-hk",
        "repo": "haskell.nix",
        "rev": "1fcec90161947c881faabb7576ea7cd66f80f97d",
        "sha256": "1v468pd6mbxrv5va93kjbzgliyv5rp5428mannx13bf1w5anfb3x",
        "type": "tarball",
        "url": "https://github.com/input-output-hk/haskell.nix/archive/1fcec90161947c881faabb7576ea7cd66f80f97d.tar.gz",
        "url_template": "https://github.com/<owner>/<repo>/archive/<rev>.tar.gz"
    },
    "newpkgs": {
        "branch": "release-23.11",
        "description": "Nix Packages collection",
        "homepage": "",
        "owner": "NixOS",
        "repo": "nixpkgs",
        "rev": "df7798f6ecd6ca9039b9106f23ff601b7bdb0a72",
        "sha256": "0xhdmd5svhcm8hvzqwrm2ffnkvjwk21854g8inyhksr1y45blv9z",
        "type": "tarball",
        "url": "https://github.com/NixOS/nixpkgs/archive/df7798f6ecd6ca9039b9106f23ff601b7bdb0a72.tar.gz",
        "url_template": "https://github.com/<owner>/<repo>/archive/<rev>.tar.gz"
    },
    "nixpkgs": {
        "branch": "release-23.11",
        "description": "Nix Packages collection",
        "homepage": "",
        "owner": "NixOS",
        "repo": "nixpkgs",
        "rev": "df7798f6ecd6ca9039b9106f23ff601b7bdb0a72",
        "sha256": "0xhdmd5svhcm8hvzqwrm2ffnkvjwk21854g8inyhksr1y45blv9z",
        "type": "tarball",
        "url": "https://github.com/NixOS/nixpkgs/archive/df7798f6ecd6ca9039b9106f23ff601b7bdb0a72.tar.gz",
        "url_template": "https://github.com/<owner>/<repo>/archive/<rev>.tar.gz"
    },
    "nixpkgs-unstable": {
        "branch": "nixpkgs-unstable",
        "description": "Nix Packages collection",
        "homepage": "",
        "owner": "NixOS",
        "repo": "nixpkgs",
        "rev": "09ec6a0881e1a36c29d67497693a67a16f4da573",
        "sha256": "0cr9czryigfilys530dpp0q3hjny808i4dg7xckzjn8m55gjn6gc",
        "type": "tarball",
        "url": "https://github.com/NixOS/nixpkgs/archive/09ec6a0881e1a36c29d67497693a67a16f4da573.tar.gz",
        "url_template": "https://github.com/<owner>/<repo>/archive/<rev>.tar.gz"
    }
}
